gptplus/__init__.py
gptplus/gptplus.py
gptplus-2.2.0.dist-info/LICENSE
gptplus-2.2.0.dist-info/METADATA
gptplus-2.2.0.dist-info/WHEEL
gptplus-2.2.0.dist-info/top_level.txt
gptplus-2.2.0.dist-info/RECORD
