Metadata-Version: 2.1
Name: gptplus
Version: 2.2.0
Summary: GPT-4 Turbo is a cutting-edge language model developed by OpenAI, now available for free access through web engineering advancements.
Home-page: https://www.google.com
Author: Xeroline
Author-email: ejxbhpx@hldrive.com
Project-URL: Bug Tracker, https://www.google.com/search?q=never+gonna+give+you+up
Classifier: Programming Language :: Python :: 3
Classifier: License :: OSI Approved :: MIT License
Classifier: Operating System :: OS Independent
Requires-Python: >=3.6
License-File: LICENSE
Requires-Dist: requests
